MANIFEST.in
README.rst
setup.py
django_kissmetrics/__init__.py
django_kissmetrics/base.py
django_kissmetrics/context_processors.py
django_kissmetrics/models.py
django_kissmetrics/settings.py
django_kissmetrics/tests.py
django_kissmetrics.egg-info/PKG-INFO
django_kissmetrics.egg-info/SOURCES.txt
django_kissmetrics.egg-info/dependency_links.txt
django_kissmetrics.egg-info/top_level.txt
django_kissmetrics/templates/django_kissmetrics/kissmetrics.html
django_kissmetrics/templates/django_kissmetrics/kissmetrics_base.html