Metadata-Version: 1.0
Name: django-kissmetrics
Version: 0.2.6
Summary: Tool for working with KISSmetrics in Django.
Home-page: http://github.com/votizen/django-kissmetrics
Author: Matt Snider
Author-email: msnider@votizen.com
License: MIT
Keywords: kissmetrics,django
Platform: any
Classifier: Programming Language :: Python
Classifier: License :: OSI Approved :: MIT License
Classifier: Operating System :: OS Independent
Classifier: Development Status :: 3 - Alpha
Classifier: Environment :: Web Environment
Classifier: Framework :: Django
Classifier: Intended Audience :: Developers
Classifier: Topic :: Software Development :: Libraries :: Python Modules
